abx_plugin_playwright/__init__.py
abx_plugin_playwright/binaries.py
abx_plugin_playwright/binproviders.py
abx_plugin_playwright/config.py
abx_plugin_playwright-2024.10.28.dist-info/METADATA
abx_plugin_playwright-2024.10.28.dist-info/WHEEL
abx_plugin_playwright-2024.10.28.dist-info/entry_points.txt
abx_plugin_playwright-2024.10.28.dist-info/RECORD
